bodhi/__init__.py
bodhi/audio_processor.py
bodhi/events.py
bodhi/transcription_client.py
bodhi/transcription_config.py
bodhi/transcription_handler.py
bodhi/transcription_response.py
bodhi/websocket_handler.py
bodhi/utils/error_utils.py
bodhi/utils/exceptions.py
bodhi/utils/logger.py
bodhi_sdk-1.2.0.dist-info/METADATA
bodhi_sdk-1.2.0.dist-info/WHEEL
bodhi_sdk-1.2.0.dist-info/top_level.txt
bodhi_sdk-1.2.0.dist-info/RECORD
