Metadata-Version: 2.4
Name: bodhi-sdk
Version: 1.2.0
Summary: Bodhi Python SDK for Streaming Speech Recognition
Home-page: https://github.com/navana-ai/bodhi-python-sdk
Author: Navana
Classifier: Programming Language :: Python :: 3
Classifier: License :: OSI Approved :: MIT License
Classifier: Operating System :: OS Independent
Requires-Python: >=3.7
Requires-Dist: requests
Requires-Dist: aiohttp
Dynamic: author
Dynamic: classifier
Dynamic: description
Dynamic: description-content-type
Dynamic: home-page
Dynamic: requires-dist
Dynamic: requires-python
Dynamic: summary
